xpanther/__init__.py
xpanther/ide.py
xpanther/launch.py
xpanther/main.py
xpanther-1.1.5.dist-info/LICENSE
xpanther-1.1.5.dist-info/METADATA
xpanther-1.1.5.dist-info/WHEEL
xpanther-1.1.5.dist-info/top_level.txt
xpanther-1.1.5.dist-info/RECORD
