Metadata-Version: 2.1
Name: xpanther
Version: 1.1.5
Summary: Find Unique Xpath of any HTML/XML element
Author-email: Flori Batusha <floribatusha0@gmail.com>
Project-URL: Check Github, https://github.com/riflosnake/XPanther
Classifier: Programming Language :: Python :: 3
Classifier: License :: OSI Approved :: MIT License
Classifier: Operating System :: OS Independent
Requires-Python: >=3.7
License-File: LICENSE
Requires-Dist: bs4 >=0.0.1
Requires-Dist: selenium >=4.9.0
Requires-Dist: requests >=2.31.0
